django_ignorebots/__init__.py
django_ignorebots-0.1.0.dist-info/AUTHORS.rst
django_ignorebots-0.1.0.dist-info/LICENSE
django_ignorebots-0.1.0.dist-info/METADATA
django_ignorebots-0.1.0.dist-info/WHEEL
django_ignorebots-0.1.0.dist-info/top_level.txt
django_ignorebots-0.1.0.dist-info/RECORD
