Metadata-Version: 2.1
Name: django-ignorebots
Version: 0.1.0
Summary: Ignore all the bots!
Home-page: https://github.com/acordiner/django_ignorebots
Author: Alister Cordiner
Author-email: acordiner@gmail.com
License: GNU General Public License v3
Keywords: django_ignorebots
Platform: UNKNOWN
Classifier: Development Status :: 2 - Pre-Alpha
Classifier: Intended Audience :: Developers
Classifier: License :: OSI Approved :: GNU General Public License v3 (GPLv3)
Classifier: Natural Language :: English
Classifier: Programming Language :: Python :: 2
Classifier: Programming Language :: Python :: 2.7
Classifier: Programming Language :: Python :: 3
Classifier: Programming Language :: Python :: 3.4
Classifier: Programming Language :: Python :: 3.5
Classifier: Programming Language :: Python :: 3.6
Classifier: Programming Language :: Python :: 3.7
